Lab09/SignExtender.v
module SignExtender(BusImm, Instr, Ctrl); 
    output [63:0] BusImm; 
    input [25:0] Instr; 
    input [1:0] Ctrl; 

    reg [63:0] result;

    always @ (*)
    begin
        // assign output, BusImm
        case(Ctrl)
            2'b00: // I-type, 12-bit immediate
            begin
                result = {52'b0, Instr[21:10]};
            end
            2'b01: // D-type, 9-bit address offset
            begin
                result = {{55{Instr[20]}}, Instr[20:12]};
            end
            2'b10: // B-type, 26-bit branch address
            begin
                result = {{36{Instr[25]}}, Instr[25:0], 2'b0};
            end
            2'b11: // CB-type, 19-bit branch address
            begin
                result = {{43{Instr[23]}}, Instr[23:5], 2'b0};
            end
        endcase
    end
    assign BusImm = result;
endmodule

Lab07/SignExtenderTest.v
`timescale 1ns / 1ps
`define STRLEN 15
module SignExtenderTest_v;

   task passTest;
      input [63:0] actualOut, expectedOut;
      input [`STRLEN*8:0] testType;
      inout [7:0]         passed;
      
      if(actualOut == expectedOut) begin $display ("%s passed", testType); passed = passed + 1; end
      else $display ("%s failed: %d should be %d", testType, actualOut, expectedOut);
   endtask
   
   task allPassed;
      input [7:0] passed;
      input [7:0] numTests;
      
      if(passed == numTests) $display ("All tests passed");
      else $display("Some tests failed");
   endtask

    // Inputs
    reg [25:0] Instr; 
    reg [1:0] Ctrl;
    reg [7:0]      passed;

    // Outputs
    wire [63:0] BusImm;


    // Instantiate the Device Under Test (DUT)
    SignExtender dut
    (
		.BusImm(BusImm), 
		.Instr(Instr), 
		.Ctrl(Ctrl)
	);

    initial //This initial block used to dump all wire/reg values to dump file
    begin
        $dumpfile("SignExtenderTest.vcd");
        $dumpvars(0,SignExtenderTest_v);
    end
    initial
    begin
        // Initialize Inputs
        Instr = 0;
        Ctrl = 0;
        passed = 0;

        // I-type test
        #90; Instr = 'b00000111110000000000000000;
        Ctrl = 0; // sign extend test with 0 MSB
        #10; passTest(BusImm, 'b011111000000, "I-type 0 test", passed);

        #90; Instr = 'b00001111110000000000000000;
        Ctrl = 0; // sign extend test with 1 MSB
        #10; passTest(BusImm, 'b111111000000, "I-type 1 test", passed);

        // D-type test
        #90; Instr = 'b00000011110000000000000000;
        Ctrl = 1; // sign extend test with 0 MSB
        #10; passTest(BusImm, 'b11110000, "D-type 0 test", passed);
        
        #90; Instr = 'b00000111100000000000000000;
        Ctrl = 1; // sign extend test with 1 MSB
        #10; passTest(BusImm, 'b1111111111111111111111111111111111111111111111111111111111100000, "D-type 1 test", passed);

        // B-type test
        #90; Instr = 'b01000111110000000000000000;
        Ctrl = 2; // sign extend test with 0 MSB
        #10; passTest(BusImm, 'b0100011111000000000000000000, "B-type 0 test", passed);

        #90; Instr = 'b10000011110000000000000000;
        Ctrl = 2; // sign extend test with 1 MSB
        #10; passTest(BusImm, 'b1111111111111111111111111111111111111000001111000000000000000000, "B-type 1 test", passed);

        // CB-type test
        #90; Instr = 'b00010111110000000000000000;
        Ctrl = 3; // sign extend test with 0 MSB
        #10; passTest(BusImm, 'b010111110000000000000, "CB-type 0 test", passed);

        #90; Instr = 'b00100111110000000000000000;
        Ctrl = 3; // sign extend test with 1 MSB
        #10; passTest(BusImm, 'b1111111111111111111111111111111111111111111100111110000000000000, "CB-type 1 test", passed);
        #90;
      
      allPassed(passed, 8);
   end
endmodule

Lab07/SignExtenderTest.vcd
$date
	Tue Oct 27 16:11:32 2020
$end
$version
	Icarus Verilog
$end
$timescale
	1ps
$end
$scope module SignExtenderTest_v $end
$var wire 64 ! BusImm [63:0] $end
$var reg 2 " Ctrl [1:0] $end
$var reg 26 # Instr [25:0] $end
$var reg 8 $ passed [7:0] $end
$scope module dut $end
$var wire 64 % BusImm [63:0] $end
$var wire 2 & Ctrl [1:0] $end
$var wire 26 ' Instr [25:0] $end
$var reg 64 ( result [63:0] $end
$upscope $end
$scope task allPassed $end
$var reg 8 ) numTests [7:0] $end
$var reg 8 * passed [7:0] $end
$upscope $end
$scope task passTest $end
$var reg 64 + actualOut [63:0] $end
$var reg 64 , expectedOut [63:0] $end
$var reg 8 - passed [7:0] $end
$var reg 121 . testType [120:0] $end
$upscope $end
$upscope $end
$enddefinitions $end
#0
$dumpvars
bx .
bx -
bx ,
bx +
bx *
bx )
b0 (
b0 '
b0 &
b0 %
b0 $
b0 #
b0 "
b0 !
$end
#90000
b11111000000 !
b11111000000 %
b11111000000 (
b111110000000000000000 #
b111110000000000000000 '
#100000
b1 $
b1 -
b1001001001011010111010001111001011100000110010100100000001100000010000001110100011001010111001101110100 .
b11111000000 ,
b11111000000 +
#190000
b111111000000 !
b111111000000 %
b111111000000 (
b1111110000000000000000 #
b1111110000000000000000 '
#200000
b10 $
b10 -
b1001001001011010111010001111001011100000110010100100000001100010010000001110100011001010111001101110100 .
b111111000000 ,
b111111000000 +
#290000
b11110000 !
b11110000 %
b11110000 (
b1 "
b1 &
b11110000000000000000 #
b11110000000000000000 '
#300000
b11 $
b11 -
b1000100001011010111010001111001011100000110010100100000001100000010000001110100011001010111001101110100 .
b11110000 ,
b11110000 +
#390000
b1111111111111111111111111111111111111111111111111111111111100000 !
b1111111111111111111111111111111111111111111111111111111111100000 %
b1111111111111111111111111111111111111111111111111111111111100000 (
b111100000000000000000 #
b111100000000000000000 '
#400000
b100 $
b100 -
b1000100001011010111010001111001011100000110010100100000001100010010000001110100011001010111001101110100 .
b1111111111111111111111111111111111111111111111111111111111100000 ,
b1111111111111111111111111111111111111111111111111111111111100000 +
#490000
b100011111000000000000000000 !
b100011111000000000000000000 %
b100011111000000000000000000 (
b10 "
b10 &
b1000111110000000000000000 #
b1000111110000000000000000 '
#500000
b101 $
b101 -
b1000010001011010111010001111001011100000110010100100000001100000010000001110100011001010111001101110100 .
b100011111000000000000000000 ,
b100011111000000000000000000 +
#590000
b1111111111111111111111111111111111111000001111000000000000000000 !
b1111111111111111111111111111111111111000001111000000000000000000 %
b1111111111111111111111111111111111111000001111000000000000000000 (
b10000011110000000000000000 #
b10000011110000000000000000 '
#600000
b110 $
b110 -
b1000010001011010111010001111001011100000110010100100000001100010010000001110100011001010111001101110100 .
b1111111111111111111111111111111111111000001111000000000000000000 ,
b1111111111111111111111111111111111111000001111000000000000000000 +
#690000
b10111110000000000000 !
b10111110000000000000 %
b10111110000000000000 (
b11 "
b11 &
b10111110000000000000000 #
b10111110000000000000000 '
#700000
b111 $
b111 -
b100001101000010001011010111010001111001011100000110010100100000001100000010000001110100011001010111001101110100 .
b10111110000000000000 ,
b10111110000000000000 +
#790000
b1111111111111111111111111111111111111111111100111110000000000000 !
b1111111111111111111111111111111111111111111100111110000000000000 %
b1111111111111111111111111111111111111111111100111110000000000000 (
b100111110000000000000000 #
b100111110000000000000000 '
#800000
b1000 $
b1000 -
b100001101000010001011010111010001111001011100000110010100100000001100010010000001110100011001010111001101110100 .
b1111111111111111111111111111111111111111111100111110000000000000 ,
b1111111111111111111111111111111111111111111100111110000000000000 +
#890000
b1000 )
b1000 *
