Lab09/NextPClogic.v
module NextPClogic(NextPC, CurrentPC, SignExtImm64, Branch, ALUZero, Uncondbranch); 

       input [63:0] CurrentPC, SignExtImm64; // SignExtImm64 is the output of the sign extender

       // Branch is true if the current instruction is a conditional branch instruction
       // Uncondbranch is true if the current instruction is an Unconditional Branch (B)
       // ALUZero is the Zero output of the ALU
       input Branch, ALUZero, Uncondbranch;
       output [63:0] NextPC; 

       // additions with a constant should have a delay of 1
       // general addition should have a delay of 2
       // any multiplexers should have a delay of 1 (includes statements inside if/else statements)
       wire [63:0] shiftSignExt = SignExtImm64 << 2; // shift left 2

       wire AND0 = Branch && ALUZero; // gate logic
       wire muxControl = AND0 || Uncondbranch; // gate logic

       reg [63:0] muxOutput; // result of MUX

       always @ (*)
       begin
              // MUX logic
              if(muxControl)
                     muxOutput <=  #3 CurrentPC + shiftSignExt;
              else
                     muxOutput <= #2 CurrentPC + 4;
       end

       assign NextPC = muxOutput; // Assign next PC
endmodule

Lab08/NextPCLogic/NextPClogicTest.v
`timescale 1ns / 1ps
`define STRLEN 15

module NextPClogicTest_v;
    // Input
    reg [63:0] CurrentPC, SignExtImm64;
    reg Branch, ALUZero, Uncondbranch;

    // Output
    wire [63:0] NextPC; 

    // Instantiate the Device Under Test (DUT)
    NextPClogic dut
    (
        .NextPC(NextPC),
        .CurrentPC(CurrentPC),
        .SignExtImm64(SignExtImm64),
        .Branch(Branch),
        .ALUZero(ALUZero),
        .Uncondbranch(Uncondbranch)
    );

    initial //This initial block used to dump all wire/reg values to dump file
    begin
        $dumpfile("NextPClogicTest.vcd");
        $dumpvars(0,NextPClogicTest_v);
    end

    initial
    begin
        // Initialize inputs
        CurrentPC = 64'h0;
        SignExtImm64 = 0;
        Branch = 0;
        ALUZero = 0;
        Uncondbranch = 0;
        
        // No branch test
        CurrentPC = 64'h8000000000000000; SignExtImm64 = 64'hffff; Branch = 0; ALUZero = 0; Uncondbranch = 0;
        #90; $display("CurrentPC = %h\nSignExtImm64 = %h\nBranch = %h\nALUZero = %h\nUncondbranch = %h", CurrentPC, SignExtImm64, Branch, ALUZero, Uncondbranch);
        if(NextPC == CurrentPC + 4)
            $display("NextPC = %h\nPASSED\n", NextPC);
        else
            $display("NextPC = %h\nFAILED\n", NextPC);

        // Positive Unconditional branch test
        CurrentPC = 64'h8000000000000000; SignExtImm64 = 64'hffff; Branch = 0; ALUZero = 0; Uncondbranch = 1;
        #90; $display("CurrentPC = %h\nSignExtImm64 = %h\nBranch = %h\nALUZero = %h\nUncondbranch = %h", CurrentPC, SignExtImm64, Branch, ALUZero, Uncondbranch);
        if(NextPC == CurrentPC + (4 * SignExtImm64))
            $display("NextPC = %h\nPASSED\n", NextPC);
        else
            $display("NextPC = %h\nFAILED\n", NextPC);
        // Negative Unconditional branch test
        CurrentPC = 64'h8000000000000000; SignExtImm64 = -64'hffff; Branch = 0; ALUZero = 0; Uncondbranch = 1;
        #90; $display("CurrentPC = %h\nSignExtImm64 = %h\nBranch = %h\nALUZero = %h\nUncondbranch = %h", CurrentPC, SignExtImm64, Branch, ALUZero, Uncondbranch);
        if(NextPC == CurrentPC + (4 * SignExtImm64))
            $display("NextPC = %h\nPASSED\n", NextPC);
        else
            $display("NextPC = %h\nFAILED\n", NextPC);

        // Conditional branch with low ALUZero test
        CurrentPC = 64'h8000000000000000; SignExtImm64 = 64'hffff; Branch = 1; ALUZero = 0; Uncondbranch = 0;
        #90; $display("CurrentPC = %h\nSignExtImm64 = %h\nBranch = %h\nALUZero = %h\nUncondbranch = %h", CurrentPC, SignExtImm64, Branch, ALUZero, Uncondbranch);
        if(NextPC == CurrentPC + 4)
            $display("NextPC = %h\nPASSED\n", NextPC);
        else
            $display("NextPC = %h\nFAILED\n", NextPC);
        // Low branch with high ALUZero test
        CurrentPC = 64'h8000000000000000; SignExtImm64 = 64'hffff; Branch = 0; ALUZero = 1; Uncondbranch = 0;
        #90; $display("CurrentPC = %h\nSignExtImm64 = %h\nBranch = %h\nALUZero = %h\nUncondbranch = %h", CurrentPC, SignExtImm64, Branch, ALUZero, Uncondbranch);
        if(NextPC == CurrentPC + 4)
            $display("NextPC = %h\nPASSED\n", NextPC);
        else
            $display("NextPC = %h\nFAILED\n", NextPC);
        // Positive Conditional branch with high ALUZero test
        CurrentPC = 64'h8000000000000000; SignExtImm64 = 64'hffff; Branch = 1; ALUZero = 1; Uncondbranch = 0;
        #90; $display("CurrentPC = %h\nSignExtImm64 = %h\nBranch = %h\nALUZero = %h\nUncondbranch = %h", CurrentPC, SignExtImm64, Branch, ALUZero, Uncondbranch);
        if(NextPC == CurrentPC + (4 * SignExtImm64))
            $display("NextPC = %h\nPASSED\n", NextPC);
        else
            $display("NextPC = %h\nFAILED\n", NextPC);
        // Negative Conditional branch with high ALUZero test
        CurrentPC = 64'h8000000000000000; SignExtImm64 = -64'hffff; Branch = 1; ALUZero = 1; Uncondbranch = 0;
        #90; $display("CurrentPC = %h\nSignExtImm64 = %h\nBranch = %h\nALUZero = %h\nUncondbranch = %h", CurrentPC, SignExtImm64, Branch, ALUZero, Uncondbranch);
        if(NextPC == CurrentPC + (4 * SignExtImm64))
            $display("NextPC = %h\nPASSED\n", NextPC);
        else
            $display("NextPC = %h\nFAILED\n", NextPC);
   end
endmodule

Lab08/NextPCLogic/NextPClogicTest.vcd
$date
	Tue Nov 10 15:08:15 2020
$end
$version
	Icarus Verilog
$end
$timescale
	1ps
$end
$scope module NextPClogicTest_v $end
$var wire 64 ! NextPC [63:0] $end
$var reg 1 " ALUZero $end
$var reg 1 # Branch $end
$var reg 64 $ CurrentPC [63:0] $end
$var reg 64 % SignExtImm64 [63:0] $end
$var reg 1 & Uncondbranch $end
$scope module dut $end
$var wire 1 " ALUZero $end
$var wire 1 ' AND0 $end
$var wire 1 # Branch $end
$var wire 64 ( CurrentPC [63:0] $end
$var wire 64 ) NextPC [63:0] $end
$var wire 64 * SignExtImm64 [63:0] $end
$var wire 1 & Uncondbranch $end
$var wire 1 + muxControl $end
$var wire 64 , shiftSignExt [63:0] $end
$var reg 64 - muxOutput [63:0] $end
$upscope $end
$upscope $end
$enddefinitions $end
#0
$dumpvars
bx -
b111111111111111100 ,
0+
b1111111111111111 *
bx )
b1000000000000000000000000000000000000000000000000000000000000000 (
0'
0&
b1111111111111111 %
b1000000000000000000000000000000000000000000000000000000000000000 $
0#
0"
bx !
$end
#2000
b1000000000000000000000000000000000000000000000000000000000000100 !
b1000000000000000000000000000000000000000000000000000000000000100 )
b1000000000000000000000000000000000000000000000000000000000000100 -
#90000
1+
1&
#93000
b1000000000000000000000000000000000000000000000111111111111111100 !
b1000000000000000000000000000000000000000000000111111111111111100 )
b1000000000000000000000000000000000000000000000111111111111111100 -
#180000
b1111111111111111111111111111111111111111111111000000000000000100 ,
b1111111111111111111111111111111111111111111111110000000000000001 %
b1111111111111111111111111111111111111111111111110000000000000001 *
#183000
b111111111111111111111111111111111111111111111000000000000000100 !
b111111111111111111111111111111111111111111111000000000000000100 )
b111111111111111111111111111111111111111111111000000000000000100 -
#270000
0+
b111111111111111100 ,
0&
1#
b1111111111111111 %
b1111111111111111 *
#272000
b1000000000000000000000000000000000000000000000000000000000000100 !
b1000000000000000000000000000000000000000000000000000000000000100 )
b1000000000000000000000000000000000000000000000000000000000000100 -
#360000
1"
0#
#450000
1+
1'
1#
#453000
b1000000000000000000000000000000000000000000000111111111111111100 !
b1000000000000000000000000000000000000000000000111111111111111100 )
b1000000000000000000000000000000000000000000000111111111111111100 -
#540000
b1111111111111111111111111111111111111111111111000000000000000100 ,
b1111111111111111111111111111111111111111111111110000000000000001 %
b1111111111111111111111111111111111111111111111110000000000000001 *
#543000
b111111111111111111111111111111111111111111111000000000000000100 !
b111111111111111111111111111111111111111111111000000000000000100 )
b111111111111111111111111111111111111111111111000000000000000100 -
