Lab09/RegisterFile.v
module RegisterFile(BusA, BusB, BusW, RA, RB, RW, RegWr, Clk);
    // Buses A, B, and W are 64 bits wide
    output [63:0] BusA; // // The contents of register RA
    output [63:0] BusB; // The contents of register RB
    input [63:0] BusW; // What is written to register RW
    input [4:0] RA, RB, RW; // Specify which registers to use
    input RegWr;
    input Clk;
    reg [63:0] registers [31:0]; // 32, 64-bit registers
    
    initial registers[31] = 64'b0; // initialize register 31 to 0
    
    assign #2 BusA = registers[RA]; // BusA reads register RA
    assign #2 BusB = registers[RB]; // BusB reads register RB

    always @ (negedge Clk) begin // check every negative clock edge
        if(RegWr && RW != 31) // ensure that register 31 is not overwritten
            registers[RW] <= #3 BusW; // data on Bus W is stored in the register specified by Rw
    end
endmodule

Lab08/Q3/RegisterFileTest.v
`timescale 1ns / 1ps
`define STRLEN 32

module RegisterFileTest_v;


	task passTest;
		input [63:0] actualOut, expectedOut;
		input [`STRLEN*8:0] testType;
		inout [7:0] passed;
	
		if(actualOut == expectedOut) begin $display ("%s passed", testType); passed = passed + 1; end
		else $display ("%s failed: %d should be %d", testType, actualOut, expectedOut);
	endtask
	
	task allPassed;
		input [7:0] passed;
		input [7:0] numTests;
		
		if(passed == numTests) $display ("All tests passed");
		else $display("Some tests failed");
	endtask

	// Inputs
	reg [63:0] BusW;
	reg [4:0] RA;
	reg [4:0] RB;
	reg [4:0] RW;
	reg RegWr;
	reg Clk;
	reg [7:0] passed;

	// Outputs
	wire [63:0] BusA;
	wire [63:0] BusB;

	// Instantiate the Unit Under Test (UUT)
	RegisterFile uut (
		.BusA(BusA), 
		.BusB(BusB), 
		.BusW(BusW), 
		.RA(RA), 
		.RB(RB), 
		.RW(RW), 
		.RegWr(RegWr), 
		.Clk(Clk)
	);

    initial //This initial block used to dump all wire/reg values to dump file
    begin
        $dumpfile("RegisterFileTest-2.vcd");
        $dumpvars(0,RegisterFileTest_v);
    end

	initial begin
		// Initialize Inputs
		BusW = 0;
		RA = 0;
		RB = 0;
		RW = 0;
		RegWr = 0;
		Clk = 1;
		passed = 0;		
		#10;

		// Initialize register values to be equal to its register number (Except 31 = 0)
		{RA, RB, RW, BusW, RegWr} = {5'd0, 5'd0, 5'd0, 64'h0, 1'b1};#10; Clk = 0; #10; Clk = 1;
		{RA, RB, RW, BusW, RegWr} = {5'd0, 5'd0, 5'd1, 64'h1, 1'b1};#10; Clk = 0; #10; Clk = 1;
		{RA, RB, RW, BusW, RegWr} = {5'd0, 5'd0, 5'd2, 64'h2, 1'b1};#10; Clk = 0; #10; Clk = 1;
		{RA, RB, RW, BusW, RegWr} = {5'd0, 5'd0, 5'd3, 64'h3, 1'b1};#10; Clk = 0; #10; Clk = 1;
		{RA, RB, RW, BusW, RegWr} = {5'd0, 5'd0, 5'd4, 64'h4, 1'b1};#10; Clk = 0; #10; Clk = 1;
		{RA, RB, RW, BusW, RegWr} = {5'd0, 5'd0, 5'd5, 64'h5, 1'b1};#10; Clk = 0; #10; Clk = 1;
		{RA, RB, RW, BusW, RegWr} = {5'd0, 5'd0, 5'd6, 64'h6, 1'b1};#10; Clk = 0; #10; Clk = 1;
		{RA, RB, RW, BusW, RegWr} = {5'd0, 5'd0, 5'd7, 64'h7, 1'b1};#10; Clk = 0; #10; Clk = 1;
		{RA, RB, RW, BusW, RegWr} = {5'd0, 5'd0, 5'd8, 64'h8, 1'b1};#10; Clk = 0; #10; Clk = 1;
		{RA, RB, RW, BusW, RegWr} = {5'd0, 5'd0, 5'd9, 64'h9, 1'b1};#10; Clk = 0; #10; Clk = 1;
		{RA, RB, RW, BusW, RegWr} = {5'd0, 5'd0, 5'd10, 64'd10, 1'b1};#10; Clk = 0; #10; Clk = 1;
		{RA, RB, RW, BusW, RegWr} = {5'd0, 5'd0, 5'd11, 64'd11, 1'b1};#10; Clk = 0; #10; Clk = 1;
		{RA, RB, RW, BusW, RegWr} = {5'd0, 5'd0, 5'd12, 64'd12, 1'b1};#10; Clk = 0; #10; Clk = 1;
		{RA, RB, RW, BusW, RegWr} = {5'd0, 5'd0, 5'd13, 64'd13, 1'b1};#10; Clk = 0; #10; Clk = 1;
		{RA, RB, RW, BusW, RegWr} = {5'd0, 5'd0, 5'd14, 64'd14, 1'b1};#10; Clk = 0; #10; Clk = 1;
		{RA, RB, RW, BusW, RegWr} = {5'd0, 5'd0, 5'd15, 64'd15, 1'b1};#10; Clk = 0; #10; Clk = 1;
		{RA, RB, RW, BusW, RegWr} = {5'd0, 5'd0, 5'd16, 64'd16, 1'b1};#10; Clk = 0; #10; Clk = 1;
		{RA, RB, RW, BusW, RegWr} = {5'd0, 5'd0, 5'd17, 64'd17, 1'b1};#10; Clk = 0; #10; Clk = 1;
		{RA, RB, RW, BusW, RegWr} = {5'd0, 5'd0, 5'd18, 64'd18, 1'b1};#10; Clk = 0; #10; Clk = 1;
		{RA, RB, RW, BusW, RegWr} = {5'd0, 5'd0, 5'd19, 64'd19, 1'b1};#10; Clk = 0; #10; Clk = 1;
		{RA, RB, RW, BusW, RegWr} = {5'd0, 5'd0, 5'd20, 64'd20, 1'b1};#10; Clk = 0; #10; Clk = 1;
		{RA, RB, RW, BusW, RegWr} = {5'd0, 5'd0, 5'd21, 64'd21, 1'b1};#10; Clk = 0; #10; Clk = 1;
		{RA, RB, RW, BusW, RegWr} = {5'd0, 5'd0, 5'd22, 64'd22, 1'b1};#10; Clk = 0; #10; Clk = 1;
		{RA, RB, RW, BusW, RegWr} = {5'd0, 5'd0, 5'd23, 64'd23, 1'b1};#10; Clk = 0; #10; Clk = 1;
		{RA, RB, RW, BusW, RegWr} = {5'd0, 5'd0, 5'd24, 64'd24, 1'b1};#10; Clk = 0; #10; Clk = 1;
		{RA, RB, RW, BusW, RegWr} = {5'd0, 5'd0, 5'd25, 64'd25, 1'b1};#10; Clk = 0; #10; Clk = 1;
		{RA, RB, RW, BusW, RegWr} = {5'd0, 5'd0, 5'd26, 64'd26, 1'b1};#10; Clk = 0; #10; Clk = 1;
		{RA, RB, RW, BusW, RegWr} = {5'd0, 5'd0, 5'd27, 64'd27, 1'b1};#10; Clk = 0; #10; Clk = 1;
		{RA, RB, RW, BusW, RegWr} = {5'd0, 5'd0, 5'd28, 64'd28, 1'b1};#10; Clk = 0; #10; Clk = 1;
		{RA, RB, RW, BusW, RegWr} = {5'd0, 5'd0, 5'd29, 64'd29, 1'b1};#10; Clk = 0; #10; Clk = 1;
		{RA, RB, RW, BusW, RegWr} = {5'd0, 5'd0, 5'd30, 64'd30, 1'b1};#10; Clk = 0; #10; Clk = 1;
		{RA, RB, RW, BusW, RegWr} = {5'd0, 5'd0, 5'd31, 64'd31, 1'b1};#10; Clk = 0; #10; Clk = 1;
		#10;

		// Add stimulus here
		{RA, RB, RW, RegWr, BusW} = {5'h0, 5'h1, 5'h0, 1'b0, 64'h0};
		#4;
		passTest(BusA, 64'h0, "Initial Value Check 0", passed);
		passTest(BusB, 64'h1, "Initial Value Check 1", passed);
		#6; Clk = 0; #10; Clk = 1;
		passTest(BusA, 64'h0, "Final Value Check 0", passed);
		passTest(BusB, 64'h1, "Final Value Check 1", passed);
		$display();

		{RA, RB, RW, RegWr, BusW} = {5'h2, 5'h3, 5'h1, 1'b0, 64'h1000};
		#4;
		passTest(BusA, 64'h2, "Initial Value Check 2", passed);
		passTest(BusB, 64'h3, "Initial Value Check 3", passed);
		#6; Clk = 0; #10; Clk = 1;
		passTest(BusA, 64'h2, "Final Value Check 2", passed);
		passTest(BusB, 64'h3, "Final Value Check 3", passed);
		$display();

		{RA, RB, RW, RegWr, BusW} = {5'h4, 5'h5, 5'h0, 1'b1, 64'h1000};
		#4;
		passTest(BusA, 64'h4, "Initial Value Check 4", passed);
		passTest(BusB, 64'h5, "Initial Value Check 5", passed);
		#6; Clk = 0; #10; Clk = 1;
		passTest(BusA, 64'h4, "Final Value Check 4", passed);
		passTest(BusB, 64'h5, "Final Value Check 5", passed);
		$display();

		{RA, RB, RW, RegWr, BusW} = {5'h6, 5'h7, 5'ha, 1'b1, 64'h1010};
		#4;
		passTest(BusA, 64'h6, "Initial Value Check 6", passed);
		passTest(BusB, 64'h7, "Initial Value Check 7", passed);
		#6; Clk = 0; #10; Clk = 1;
		passTest(BusA, 64'h6, "Final Value Check 6", passed);
		passTest(BusB, 64'h7, "Final Value Check 7", passed);
		$display();

		{RA, RB, RW, RegWr, BusW} = {5'h8, 5'h9, 5'hb, 1'b1, 64'h103000};
		#4;
		passTest(BusA, 64'h8, "Initial Value Check 8", passed);
		passTest(BusB, 64'h9, "Initial Value Check 9", passed);
		#6; Clk = 0; #10; Clk = 1;
		passTest(BusA, 64'h8, "Final Value Check 8", passed);
		passTest(BusB, 64'h9, "Final Value Check 9", passed);
		$display();

		{RA, RB, RW, RegWr, BusW} = {5'ha, 5'hb, 5'hc, 1'b0, 64'h0};
		#4;
		passTest(BusA, 64'h1010, "Initial Value Check 10", passed);
		passTest(BusB, 64'h103000, "Initial Value Check 11", passed);
		#6; Clk = 0; #10; Clk = 1;
		passTest(BusA, 64'h1010, "Final Value Check 10", passed);
		passTest(BusB, 64'h103000, "Final Value Check 11", passed);
		$display();

		{RA, RB, RW, RegWr, BusW} = {5'hc, 5'hd, 5'hd, 1'b1, 64'habcd};
		#4;
		passTest(BusA, 64'hc, "Initial Value Check 12", passed);
		passTest(BusB, 64'hd, "Initial Value Check 13", passed);
		#6; Clk = 0; #10; Clk = 1;
		passTest(BusA, 64'hc, "Final Value Check 12", passed);
		passTest(BusB, 64'habcd, "Final Value Check 13", passed);
		$display();

		{RA, RB, RW, RegWr, BusW} = {5'he, 5'hf, 5'he, 1'b0, 64'h9080009};
		#4;
		passTest(BusA, 64'he, "Initial Value Check 14", passed);
		passTest(BusB, 64'hf, "Initial Value Check 15", passed);
		#6; Clk = 0; #10; Clk = 1;
		passTest(BusA, 64'he, "Final Value Check 14", passed);
		passTest(BusB, 64'hf, "Final Value Check 15", passed);
		$display();
		allPassed(passed, 32);
	end
      
endmodule

Lab08/Q3/RegisterFileTest-2.vcd
$date
	Tue Nov 10 14:33:20 2020
$end
$version
	Icarus Verilog
$end
$timescale
	1ps
$end
$scope module RegisterFileTest_v $end
$var wire 64 ! BusB [63:0] $end
$var wire 64 " BusA [63:0] $end
$var reg 64 # BusW [63:0] $end
$var reg 1 $ Clk $end
$var reg 5 % RA [4:0] $end
$var reg 5 & RB [4:0] $end
$var reg 5 ' RW [4:0] $end
$var reg 1 ( RegWr $end
$var reg 8 ) passed [7:0] $end
$scope module uut $end
$var wire 64 * BusA [63:0] $end
$var wire 64 + BusB [63:0] $end
$var wire 64 , BusW [63:0] $end
$var wire 1 $ Clk $end
$var wire 5 - RA [4:0] $end
$var wire 5 . RB [4:0] $end
$var wire 5 / RW [4:0] $end
$var wire 1 ( RegWr $end
$upscope $end
$scope task allPassed $end
$var reg 8 0 numTests [7:0] $end
$var reg 8 1 passed [7:0] $end
$upscope $end
$scope task passTest $end
$var reg 64 2 actualOut [63:0] $end
$var reg 64 3 expectedOut [63:0] $end
$var reg 8 4 passed [7:0] $end
$var reg 257 5 testType [256:0] $end
$upscope $end
$upscope $end
$enddefinitions $end
#0
$dumpvars
bx 5
bx 4
bx 3
bx 2
bx 1
bx 0
b0 /
b0 .
b0 -
b0 ,
bx +
bx *
b0 )
0(
b0 '
b0 &
b0 %
1$
b0 #
bx "
bx !
$end
#10000
1(
#20000
0$
#25000
b0 "
b0 *
b0 !
b0 +
#30000
b1 '
b1 /
b1 #
b1 ,
1$
#40000
0$
#50000
b10 '
b10 /
b10 #
b10 ,
1$
#60000
0$
#70000
b11 '
b11 /
b11 #
b11 ,
1$
#80000
0$
#90000
b100 '
b100 /
b100 #
b100 ,
1$
#100000
0$
#110000
b101 '
b101 /
b101 #
b101 ,
1$
#120000
0$
#130000
b110 '
b110 /
b110 #
b110 ,
1$
#140000
0$
#150000
b111 '
b111 /
b111 #
b111 ,
1$
#160000
0$
#170000
b1000 '
b1000 /
b1000 #
b1000 ,
1$
#180000
0$
#190000
b1001 '
b1001 /
b1001 #
b1001 ,
1$
#200000
0$
#210000
b1010 '
b1010 /
b1010 #
b1010 ,
1$
#220000
0$
#230000
b1011 '
b1011 /
b1011 #
b1011 ,
1$
#240000
0$
#250000
b1100 '
b1100 /
b1100 #
b1100 ,
1$
#260000
0$
#270000
b1101 '
b1101 /
b1101 #
b1101 ,
1$
#280000
0$
#290000
b1110 '
b1110 /
b1110 #
b1110 ,
1$
#300000
0$
#310000
b1111 '
b1111 /
b1111 #
b1111 ,
1$
#320000
0$
#330000
b10000 '
b10000 /
b10000 #
b10000 ,
1$
#340000
0$
#350000
b10001 '
b10001 /
b10001 #
b10001 ,
1$
#360000
0$
#370000
b10010 '
b10010 /
b10010 #
b10010 ,
1$
#380000
0$
#390000
b10011 '
b10011 /
b10011 #
b10011 ,
1$
#400000
0$
#410000
b10100 '
b10100 /
b10100 #
b10100 ,
1$
#420000
0$
#430000
b10101 '
b10101 /
b10101 #
b10101 ,
1$
#440000
0$
#450000
b10110 '
b10110 /
b10110 #
b10110 ,
1$
#460000
0$
#470000
b10111 '
b10111 /
b10111 #
b10111 ,
1$
#480000
0$
#490000
b11000 '
b11000 /
b11000 #
b11000 ,
1$
#500000
0$
#510000
b11001 '
b11001 /
b11001 #
b11001 ,
1$
#520000
0$
#530000
b11010 '
b11010 /
b11010 #
b11010 ,
1$
#540000
0$
#550000
b11011 '
b11011 /
b11011 #
b11011 ,
1$
#560000
0$
#570000
b11100 '
b11100 /
b11100 #
b11100 ,
1$
#580000
0$
#590000
b11101 '
b11101 /
b11101 #
b11101 ,
1$
#600000
0$
#610000
b11110 '
b11110 /
b11110 #
b11110 ,
1$
#620000
0$
#630000
b11111 '
b11111 /
b11111 #
b11111 ,
1$
#640000
0$
#650000
1$
#660000
b1 &
b1 .
b0 '
b0 /
0(
b0 #
b0 ,
#662000
b1 !
b1 +
#664000
b10 )
b10 4
b10010010110111001101001011101000110100101100001011011000010000001010110011000010110110001110101011001010010000001000011011010000110010101100011011010110010000000110001 5
b1 3
b1 2
#670000
0$
#680000
b10 %
b10 -
b11 &
b11 .
b1 '
b1 /
b1000000000000 #
b1000000000000 ,
b100 )
b100 4
b1000110011010010110111001100001011011000010000001010110011000010110110001110101011001010010000001000011011010000110010101100011011010110010000000110001 5
b1 3
b1 2
1$
#682000
b10 "
b10 *
b11 !
b11 +
#684000
b110 )
b110 4
b10010010110111001101001011101000110100101100001011011000010000001010110011000010110110001110101011001010010000001000011011010000110010101100011011010110010000000110011 5
b11 3
b11 2
#690000
0$
#700000
b100 %
b100 -
b101 &
b101 .
b0 '
b0 /
1(
b1000 )
b1000 4
b1000110011010010110111001100001011011000010000001010110011000010110110001110101011001010010000001000011011010000110010101100011011010110010000000110011 5
b11 3
b11 2
1$
#702000
b100 "
b100 *
b101 !
b101 +
#704000
b1010 )
b1010 4
b10010010110111001101001011101000110100101100001011011000010000001010110011000010110110001110101011001010010000001000011011010000110010101100011011010110010000000110101 5
b101 3
b101 2
#710000
0$
#720000
b110 %
b110 -
b111 &
b111 .
b1010 '
b1010 /
b1000000010000 #
b1000000010000 ,
b1100 )
b1100 4
b1000110011010010110111001100001011011000010000001010110011000010110110001110101011001010010000001000011011010000110010101100011011010110010000000110101 5
b101 3
b101 2
1$
#722000
b110 "
b110 *
b111 !
b111 +
#724000
b1110 )
b1110 4
b10010010110111001101001011101000110100101100001011011000010000001010110011000010110110001110101011001010010000001000011011010000110010101100011011010110010000000110111 5
b111 3
b111 2
#730000
0$
#740000
b1000 %
b1000 -
b1001 &
b1001 .
b1011 '
b1011 /
b100000011000000000000 #
b100000011000000000000 ,
b10000 )
b10000 4
b1000110011010010110111001100001011011000010000001010110011000010110110001110101011001010010000001000011011010000110010101100011011010110010000000110111 5
b111 3
b111 2
1$
#742000
b1000 "
b1000 *
b1001 !
b1001 +
#744000
b10010 )
b10010 4
b10010010110111001101001011101000110100101100001011011000010000001010110011000010110110001110101011001010010000001000011011010000110010101100011011010110010000000111001 5
b1001 3
b1001 2
#750000
0$
#760000
b1010 %
b1010 -
b1011 &
b1011 .
b1100 '
b1100 /
0(
b0 #
b0 ,
b10100 )
b10100 4
b1000110011010010110111001100001011011000010000001010110011000010110110001110101011001010010000001000011011010000110010101100011011010110010000000111001 5
b1001 3
b1001 2
1$
#762000
b1000000010000 "
b1000000010000 *
b100000011000000000000 !
b100000011000000000000 +
#764000
b10110 )
b10110 4
b1001001011011100110100101110100011010010110000101101100001000000101011001100001011011000111010101100101001000000100001101101000011001010110001101101011001000000011000100110001 5
b100000011000000000000 3
b100000011000000000000 2
#770000
0$
#780000
b1100 %
b1100 -
b1101 &
b1101 .
b1101 '
b1101 /
1(
b1010101111001101 #
b1010101111001101 ,
b11000 )
b11000 4
b100011001101001011011100110000101101100001000000101011001100001011011000111010101100101001000000100001101101000011001010110001101101011001000000011000100110001 5
b100000011000000000000 3
b100000011000000000000 2
1$
#782000
b1100 "
b1100 *
b1101 !
b1101 +
#784000
b11010 )
b11010 4
b1001001011011100110100101110100011010010110000101101100001000000101011001100001011011000111010101100101001000000100001101101000011001010110001101101011001000000011000100110011 5
b1101 3
b1101 2
#790000
0$
#795000
b1010101111001101 !
b1010101111001101 +
#800000
b1110 %
b1110 -
b1111 &
b1111 .
b1110 '
b1110 /
0(
b1001000010000000000000001001 #
b1001000010000000000000001001 ,
b11100 )
b11100 4
b100011001101001011011100110000101101100001000000101011001100001011011000111010101100101001000000100001101101000011001010110001101101011001000000011000100110011 5
b1010101111001101 3
b1010101111001101 2
1$
#802000
b1110 "
b1110 *
b1111 !
b1111 +
#804000
b11110 )
b11110 4
b1001001011011100110100101110100011010010110000101101100001000000101011001100001011011000111010101100101001000000100001101101000011001010110001101101011001000000011000100110101 5
b1111 3
b1111 2
#810000
0$
#820000
b100000 0
b100000 1
b100000 )
b100000 4
b100011001101001011011100110000101101100001000000101011001100001011011000111010101100101001000000100001101101000011001010110001101101011001000000011000100110101 5
b1111 3
b1111 2
1$
